Metadata-Version: 2.1
Name: craxkhash
Version: 1.0.0
Summary: Craxk is a UNIQUE AND NON-REPLICABLE Hash that uses data from the hardware where it is executed to form a hash that can only be reproduced by a single machine.
Home-page: https://github.com/ZaikoARG/Craxk
Author: ZaikoARG
Author-email: zaikoarg@gmail.com
License: MIT
Platform: UNKNOWN
Classifier: License :: OSI Approved :: MIT License
Classifier: Programming Language :: Python :: 3
Classifier: Programming Language :: Python :: 3.7
